README.rst
setup.py
sentry_telegram_app/__init__.py
sentry_telegram_app/plugin.py
sentry_telegram_app.egg-info/PKG-INFO
sentry_telegram_app.egg-info/SOURCES.txt
sentry_telegram_app.egg-info/dependency_links.txt
sentry_telegram_app.egg-info/entry_points.txt
sentry_telegram_app.egg-info/top_level.txt