Metadata-Version: 2.1
Name: sentry-telegram-app
Version: 0.4.5
Summary: Fork. Plugin for Sentry which allows sending notification via Telegram messenger.
Home-page: https://github.com/urpyLLIKa/sentry-telegram-app
Author: Dmitry Brazhnikov
Author-email: todim@bk.ru
License: MIT
Platform: UNKNOWN
Classifier: Development Status :: 5 - Production/Stable
Classifier: Environment :: Console
Classifier: Intended Audience :: Developers
Classifier: Intended Audience :: System Administrators
Classifier: License :: OSI Approved :: MIT License
Classifier: Operating System :: OS Independent
Classifier: Programming Language :: Python
Classifier: Programming Language :: Python :: 3.6
Classifier: Programming Language :: Python :: Implementation :: CPython
Classifier: Topic :: Software Development :: Bug Tracking
Classifier: Topic :: Software Development :: Quality Assurance
Classifier: Topic :: System :: Monitoring
